[
  {
    "id": 2,
    "name": "Смартфон",
    "price": 30000,
    "description": "Современный смартфон с камерой 48 Мп",
    "categories": [
      "Электроника"
    ]
  },
  {
    "id": 3,
    "name": "Книга",
    "price": 500,
    "description": "Интересная книга по программированию",
    "categories": [
      "Книги"
    ]
  },
  {
    "id": 4,
    "name": "Наушники",
    "price": 5000,
    "description": "Беспроводные наушники с шумоподавлением",
    "categories": [
      "Электроника",
      "Аксессуары"
    ]
  },
  {
    "id": 5,
    "name": "Футболка",
    "price": 1500,
    "description": "Хлопковая футболка с принтом",
    "categories": [
      "Одежда"
    ]
  }
]